{
  "targetDate": "2025-05-25",
  "location": {
    "name": "Richmond, VA",
    "lat": 37.5407,
    "lon": -77.436
  },
  "note": "Backfill uses Open-Meteo Historical Forecast (archived forecasts) vs Open-Meteo Historical Weather (reanalysis) for actuals.",
  "forecast": {
    "highF": 75,
    "lowF": 49.9
  },
  "actual": {
    "highF": 72.8,
    "lowF": 53.1
  },
  "errors": {
    "highAbsF": 2.2,
    "lowAbsF": 3.2,
    "overallAbsF": 2.7
  },
  "computedAt": "2026-03-08T16:31:11.112-04:00"
}
