{
  "targetDate": "2026-02-01",
  "location": {
    "name": "Richmond, VA",
    "lat": 37.5407,
    "lon": -77.436
  },
  "note": "Backfill uses Open-Meteo Historical Forecast (archived forecasts) vs Open-Meteo Historical Weather (reanalysis) for actuals.",
  "forecast": {
    "highF": 29.2,
    "lowF": 16.8
  },
  "actual": {
    "highF": 28.9,
    "lowF": 15
  },
  "errors": {
    "highAbsF": 0.3,
    "lowAbsF": 1.8,
    "overallAbsF": 1.1
  },
  "computedAt": "2026-03-08T16:31:11.112-04:00"
}
