{
  "targetDate": "2026-04-14",
  "observedFromStation": "KRIC",
  "observationCount": 312,
  "observed": {
    "highF": 89.6,
    "lowF": 60.8,
    "maxWindMph": 66.3,
    "precipOccurred": false
  },
  "snapshotUsed": "2026-04-13_for_2026-04-14.json",
  "scores": [
    {
      "provider": "openMeteo",
      "predicted": {
        "highF": 89.1,
        "lowF": 64.3,
        "windMph": 21.5,
        "precipProbability": 4,
        "precipExpected": false
      },
      "errors": {
        "highAbsF": 0.5,
        "lowAbsF": 3.5,
        "windAbsMph": 44.8,
        "precipEventMiss": 0,
        "overallAbsF": 16.3
      }
    },
    {
      "provider": "metNo",
      "predicted": {
        "highF": 89.6,
        "lowF": 62.4,
        "windMph": 12.8,
        "precipProbability": null,
        "precipExpected": false
      },
      "errors": {
        "highAbsF": 0,
        "lowAbsF": 1.6,
        "windAbsMph": 53.5,
        "precipEventMiss": 0,
        "overallAbsF": 18.4
      }
    },
    {
      "provider": "nws",
      "predicted": {
        "highF": 91,
        "lowF": 67,
        "windMph": 12,
        "precipProbability": 7,
        "precipExpected": false
      },
      "errors": {
        "highAbsF": 1.4,
        "lowAbsF": 6.2,
        "windAbsMph": 54.3,
        "precipEventMiss": 0,
        "overallAbsF": 20.6
      }
    }
  ],
  "computedAt": "2026-04-15T07:17:39.481-04:00"
}
