{
  "location": {
    "name": "Richmond, VA",
    "lat": 37.5407,
    "lon": -77.436
  },
  "generatedAt": "2026-03-10T01:13:37.902-04:00",
  "days": [
    {
      "date": "2026-03-09",
      "sources": {
        "nws": {
          "date": "2026-03-09",
          "summary": "Mostly Clear",
          "precipProbability": 0,
          "rain": false,
          "snow": false,
          "thunder": false
        },
        "openMeteo": null,
        "metNo": null
      },
      "consensus": {
        "rainSignal": "off",
        "snowSignal": "off",
        "thunderSignal": "off",
        "avgPrecipProbability": 0,
        "summary": "Mostly quiet signal"
      }
    },
    {
      "date": "2026-03-10",
      "sources": {
        "nws": {
          "date": "2026-03-10",
          "summary": "Sunny",
          "precipProbability": 5,
          "rain": false,
          "snow": false,
          "thunder": false
        },
        "openMeteo": {
          "date": "2026-03-10",
          "summary": "Overcast",
          "precipProbability": 2,
          "rain": false,
          "snow": false,
          "thunder": false
        },
        "metNo": {
          "date": "2026-03-10",
          "summary": "Clearsky Night",
          "precipProbability": null,
          "rain": false,
          "snow": false,
          "thunder": false
        }
      },
      "consensus": {
        "rainSignal": "off",
        "snowSignal": "off",
        "thunderSignal": "off",
        "avgPrecipProbability": 3.5,
        "summary": "Mostly quiet signal"
      }
    },
    {
      "date": "2026-03-11",
      "sources": {
        "nws": {
          "date": "2026-03-11",
          "summary": "Partly Sunny then Slight Chance Rain Showers",
          "precipProbability": 35,
          "rain": true,
          "snow": false,
          "thunder": true
        },
        "openMeteo": {
          "date": "2026-03-11",
          "summary": "Overcast",
          "precipProbability": 13,
          "rain": false,
          "snow": false,
          "thunder": false
        },
        "metNo": {
          "date": "2026-03-11",
          "summary": "Partlycloudy Night",
          "precipProbability": null,
          "rain": false,
          "snow": false,
          "thunder": false
        }
      },
      "consensus": {
        "rainSignal": "weak",
        "snowSignal": "off",
        "thunderSignal": "weak",
        "avgPrecipProbability": 24,
        "summary": "Mostly quiet signal"
      }
    },
    {
      "date": "2026-03-12",
      "sources": {
        "nws": {
          "date": "2026-03-12",
          "summary": "Showers And Thunderstorms",
          "precipProbability": 85,
          "rain": true,
          "snow": false,
          "thunder": true
        },
        "openMeteo": {
          "date": "2026-03-12",
          "summary": "Light snow",
          "precipProbability": 81,
          "rain": false,
          "snow": true,
          "thunder": false
        },
        "metNo": {
          "date": "2026-03-12",
          "summary": "Partlycloudy Night",
          "precipProbability": null,
          "rain": true,
          "snow": false,
          "thunder": false
        }
      },
      "consensus": {
        "rainSignal": "medium",
        "snowSignal": "weak",
        "thunderSignal": "weak",
        "avgPrecipProbability": 83,
        "summary": "Rain signal present"
      }
    },
    {
      "date": "2026-03-13",
      "sources": {
        "nws": {
          "date": "2026-03-13",
          "summary": "Sunny",
          "precipProbability": 2,
          "rain": false,
          "snow": false,
          "thunder": false
        },
        "openMeteo": {
          "date": "2026-03-13",
          "summary": "Overcast",
          "precipProbability": 5,
          "rain": false,
          "snow": false,
          "thunder": false
        },
        "metNo": {
          "date": "2026-03-13",
          "summary": "Clearsky Night",
          "precipProbability": null,
          "rain": false,
          "snow": false,
          "thunder": false
        }
      },
      "consensus": {
        "rainSignal": "off",
        "snowSignal": "off",
        "thunderSignal": "off",
        "avgPrecipProbability": 3.5,
        "summary": "Mostly quiet signal"
      }
    },
    {
      "date": "2026-03-14",
      "sources": {
        "nws": {
          "date": "2026-03-14",
          "summary": "Mostly Sunny",
          "precipProbability": 3,
          "rain": false,
          "snow": false,
          "thunder": false
        },
        "openMeteo": {
          "date": "2026-03-14",
          "summary": "Overcast",
          "precipProbability": 2,
          "rain": false,
          "snow": false,
          "thunder": false
        },
        "metNo": {
          "date": "2026-03-14",
          "summary": "Partlycloudy Night",
          "precipProbability": null,
          "rain": false,
          "snow": false,
          "thunder": false
        }
      },
      "consensus": {
        "rainSignal": "off",
        "snowSignal": "off",
        "thunderSignal": "off",
        "avgPrecipProbability": 2.5,
        "summary": "Mostly quiet signal"
      }
    },
    {
      "date": "2026-03-15",
      "sources": {
        "nws": {
          "date": "2026-03-15",
          "summary": "Mostly Sunny",
          "precipProbability": 52,
          "rain": true,
          "snow": false,
          "thunder": false
        },
        "openMeteo": {
          "date": "2026-03-15",
          "summary": "Overcast",
          "precipProbability": 45,
          "rain": false,
          "snow": false,
          "thunder": false
        },
        "metNo": {
          "date": "2026-03-15",
          "summary": "Fair Night",
          "precipProbability": null,
          "rain": false,
          "snow": false,
          "thunder": false
        }
      },
      "consensus": {
        "rainSignal": "weak",
        "snowSignal": "off",
        "thunderSignal": "off",
        "avgPrecipProbability": 48.5,
        "summary": "Mostly quiet signal"
      }
    }
  ]
}
