{
  "location": {
    "name": "Richmond, VA",
    "lat": 37.5407,
    "lon": -77.436
  },
  "generatedAt": "2026-03-25T08:05:47.883-04:00",
  "days": [
    {
      "date": "2026-03-25",
      "sources": {
        "nws": {
          "date": "2026-03-25",
          "summary": "Mostly Sunny",
          "precipProbability": 4,
          "windMph": 7,
          "rain": false,
          "snow": false,
          "thunder": false
        },
        "openMeteo": {
          "date": "2026-03-25",
          "summary": "Overcast",
          "precipProbability": 2,
          "windMph": 18.3,
          "rain": false,
          "snow": false,
          "thunder": false
        },
        "metNo": {
          "date": "2026-03-25",
          "summary": "Fair Day",
          "precipProbability": null,
          "windMph": 11.2,
          "rain": false,
          "snow": false,
          "thunder": false
        }
      },
      "consensus": {
        "rainSignal": "off",
        "snowSignal": "off",
        "thunderSignal": "off",
        "avgPrecipProbability": 3,
        "avgWindMph": 12.2,
        "windSignal": "weak",
        "summary": "Mostly quiet signal"
      },
      "writeup": "Weather looks fairly quiet with temperatures near 62° / 39°. A warmer turn follows the next day."
    },
    {
      "date": "2026-03-26",
      "sources": {
        "nws": {
          "date": "2026-03-26",
          "summary": "Mostly Sunny",
          "precipProbability": 12,
          "windMph": 13,
          "rain": false,
          "snow": false,
          "thunder": false
        },
        "openMeteo": {
          "date": "2026-03-26",
          "summary": "Overcast",
          "precipProbability": 5,
          "windMph": 29.3,
          "rain": false,
          "snow": false,
          "thunder": false
        },
        "metNo": {
          "date": "2026-03-26",
          "summary": "Fair Night",
          "precipProbability": null,
          "windMph": 13.6,
          "rain": false,
          "snow": false,
          "thunder": false
        }
      },
      "consensus": {
        "rainSignal": "off",
        "snowSignal": "off",
        "thunderSignal": "off",
        "avgPrecipProbability": 8.5,
        "avgWindMph": 18.6,
        "windSignal": "medium",
        "summary": "Mostly quiet signal"
      },
      "writeup": "It looks breezy to windy with temperatures near 77° / 52° plus wind around 19 mph."
    },
    {
      "date": "2026-03-27",
      "sources": {
        "nws": {
          "date": "2026-03-27",
          "summary": "Rain Showers Likely",
          "precipProbability": 73,
          "windMph": 13,
          "rain": true,
          "snow": false,
          "thunder": false
        },
        "openMeteo": {
          "date": "2026-03-27",
          "summary": "Rain",
          "precipProbability": 76,
          "windMph": 36.5,
          "rain": true,
          "snow": false,
          "thunder": false
        },
        "metNo": {
          "date": "2026-03-27",
          "summary": "Cloudy",
          "precipProbability": null,
          "windMph": 14.5,
          "rain": true,
          "snow": false,
          "thunder": false
        }
      },
      "consensus": {
        "rainSignal": "strong",
        "snowSignal": "off",
        "thunderSignal": "off",
        "avgPrecipProbability": 74.5,
        "avgWindMph": 21.3,
        "windSignal": "strong",
        "summary": "Rain signal present"
      },
      "writeup": "Showers look likely with temperatures near 76° / 45° and about 75% average precipitation signal plus wind around 21 mph. A sharp cooler turn follows the next day."
    },
    {
      "date": "2026-03-28",
      "sources": {
        "nws": {
          "date": "2026-03-28",
          "summary": "Sunny",
          "precipProbability": 12,
          "windMph": 8,
          "rain": false,
          "snow": false,
          "thunder": false
        },
        "openMeteo": {
          "date": "2026-03-28",
          "summary": "Overcast",
          "precipProbability": 57,
          "windMph": 24.2,
          "rain": false,
          "snow": false,
          "thunder": false
        },
        "metNo": {
          "date": "2026-03-28",
          "summary": "Fair Night",
          "precipProbability": null,
          "windMph": 13.2,
          "rain": false,
          "snow": false,
          "thunder": false
        }
      },
      "consensus": {
        "rainSignal": "off",
        "snowSignal": "off",
        "thunderSignal": "off",
        "avgPrecipProbability": 34.5,
        "avgWindMph": 15.1,
        "windSignal": "medium",
        "summary": "Mostly quiet signal"
      },
      "writeup": "It looks breezy to windy with temperatures near 52° / 36° plus wind around 15 mph."
    },
    {
      "date": "2026-03-29",
      "sources": {
        "nws": {
          "date": "2026-03-29",
          "summary": "Sunny",
          "precipProbability": 3,
          "windMph": 7,
          "rain": false,
          "snow": false,
          "thunder": false
        },
        "openMeteo": {
          "date": "2026-03-29",
          "summary": "Overcast",
          "precipProbability": 1,
          "windMph": 24.6,
          "rain": false,
          "snow": false,
          "thunder": false
        },
        "metNo": {
          "date": "2026-03-29",
          "summary": "Clearsky Night",
          "precipProbability": null,
          "windMph": 11.2,
          "rain": false,
          "snow": false,
          "thunder": false
        }
      },
      "consensus": {
        "rainSignal": "off",
        "snowSignal": "off",
        "thunderSignal": "off",
        "avgPrecipProbability": 2,
        "avgWindMph": 14.3,
        "windSignal": "medium",
        "summary": "Mostly quiet signal"
      },
      "writeup": "It looks breezy to windy with temperatures near 59° / 38°."
    },
    {
      "date": "2026-03-30",
      "sources": {
        "nws": {
          "date": "2026-03-30",
          "summary": "Mostly Sunny",
          "precipProbability": 9,
          "windMph": 12,
          "rain": false,
          "snow": false,
          "thunder": false
        },
        "openMeteo": {
          "date": "2026-03-30",
          "summary": "Light drizzle",
          "precipProbability": 8,
          "windMph": 29.8,
          "rain": true,
          "snow": false,
          "thunder": false
        },
        "metNo": {
          "date": "2026-03-30",
          "summary": "Partlycloudy Night",
          "precipProbability": null,
          "windMph": 13,
          "rain": false,
          "snow": false,
          "thunder": false
        }
      },
      "consensus": {
        "rainSignal": "weak",
        "snowSignal": "off",
        "thunderSignal": "off",
        "avgPrecipProbability": 8.5,
        "avgWindMph": 18.3,
        "windSignal": "medium",
        "summary": "Mostly quiet signal"
      },
      "writeup": "It looks breezy to windy with temperatures near 70° / 47° plus wind around 18 mph."
    },
    {
      "date": "2026-03-31",
      "sources": {
        "nws": {
          "date": "2026-03-31",
          "summary": "Mostly Sunny",
          "precipProbability": 20,
          "windMph": 9,
          "rain": true,
          "snow": false,
          "thunder": false
        },
        "openMeteo": {
          "date": "2026-03-31",
          "summary": "Overcast",
          "precipProbability": 14,
          "windMph": 33.8,
          "rain": false,
          "snow": false,
          "thunder": false
        },
        "metNo": {
          "date": "2026-03-31",
          "summary": "Heavyrain",
          "precipProbability": null,
          "windMph": 9.2,
          "rain": true,
          "snow": false,
          "thunder": false
        }
      },
      "consensus": {
        "rainSignal": "medium",
        "snowSignal": "off",
        "thunderSignal": "off",
        "avgPrecipProbability": 17,
        "avgWindMph": 17.3,
        "windSignal": "strong",
        "summary": "Rain signal present"
      },
      "writeup": "Showers look likely with temperatures near 77° / 56° plus wind around 17 mph."
    }
  ]
}
