{
  "location": {
    "name": "Richmond, VA",
    "lat": 37.5407,
    "lon": -77.436
  },
  "generatedAt": "2026-03-24T08:06:34.830-04:00",
  "days": [
    {
      "date": "2026-03-24",
      "sources": {
        "nws": {
          "date": "2026-03-24",
          "summary": "Sunny",
          "precipProbability": 1,
          "windMph": 6,
          "rain": false,
          "snow": false,
          "thunder": false
        },
        "openMeteo": {
          "date": "2026-03-24",
          "summary": "Overcast",
          "precipProbability": 0,
          "windMph": 26.4,
          "rain": false,
          "snow": false,
          "thunder": false
        },
        "metNo": {
          "date": "2026-03-24",
          "summary": "Partlycloudy Day",
          "precipProbability": null,
          "windMph": 9.2,
          "rain": false,
          "snow": false,
          "thunder": false
        }
      },
      "consensus": {
        "rainSignal": "off",
        "snowSignal": "off",
        "thunderSignal": "off",
        "avgPrecipProbability": 0.5,
        "avgWindMph": 13.9,
        "windSignal": "medium",
        "summary": "Mostly quiet signal"
      },
      "writeup": "It looks breezy to windy with temperatures near 53° / 35°."
    },
    {
      "date": "2026-03-25",
      "sources": {
        "nws": {
          "date": "2026-03-25",
          "summary": "Mostly Sunny",
          "precipProbability": 1,
          "windMph": 8,
          "rain": false,
          "snow": false,
          "thunder": false
        },
        "openMeteo": {
          "date": "2026-03-25",
          "summary": "Overcast",
          "precipProbability": 2,
          "windMph": 19.5,
          "rain": false,
          "snow": false,
          "thunder": false
        },
        "metNo": {
          "date": "2026-03-25",
          "summary": "Partlycloudy Night",
          "precipProbability": null,
          "windMph": 8.9,
          "rain": false,
          "snow": false,
          "thunder": false
        }
      },
      "consensus": {
        "rainSignal": "off",
        "snowSignal": "off",
        "thunderSignal": "off",
        "avgPrecipProbability": 1.5,
        "avgWindMph": 12.1,
        "windSignal": "weak",
        "summary": "Mostly quiet signal"
      },
      "writeup": "Weather looks fairly quiet with temperatures near 63° / 38°. A warmer turn follows the next day."
    },
    {
      "date": "2026-03-26",
      "sources": {
        "nws": {
          "date": "2026-03-26",
          "summary": "Mostly Sunny",
          "precipProbability": 16,
          "windMph": 12,
          "rain": true,
          "snow": false,
          "thunder": false
        },
        "openMeteo": {
          "date": "2026-03-26",
          "summary": "Overcast",
          "precipProbability": 3,
          "windMph": 34.9,
          "rain": false,
          "snow": false,
          "thunder": false
        },
        "metNo": {
          "date": "2026-03-26",
          "summary": "Partlycloudy Night",
          "precipProbability": null,
          "windMph": 13.6,
          "rain": false,
          "snow": false,
          "thunder": false
        }
      },
      "consensus": {
        "rainSignal": "weak",
        "snowSignal": "off",
        "thunderSignal": "off",
        "avgPrecipProbability": 9.5,
        "avgWindMph": 20.2,
        "windSignal": "strong",
        "summary": "Mostly quiet signal"
      },
      "writeup": "It looks breezy to windy with temperatures near 77° / 54° plus wind around 20 mph."
    },
    {
      "date": "2026-03-27",
      "sources": {
        "nws": {
          "date": "2026-03-27",
          "summary": "Rain Showers Likely",
          "precipProbability": 56,
          "windMph": 12,
          "rain": true,
          "snow": true,
          "thunder": false
        },
        "openMeteo": {
          "date": "2026-03-27",
          "summary": "Rain",
          "precipProbability": 54,
          "windMph": 37.6,
          "rain": true,
          "snow": false,
          "thunder": false
        },
        "metNo": {
          "date": "2026-03-27",
          "summary": "Cloudy",
          "precipProbability": null,
          "windMph": 14.1,
          "rain": true,
          "snow": false,
          "thunder": false
        }
      },
      "consensus": {
        "rainSignal": "strong",
        "snowSignal": "weak",
        "thunderSignal": "off",
        "avgPrecipProbability": 55,
        "avgWindMph": 21.2,
        "windSignal": "strong",
        "summary": "Rain signal present"
      },
      "writeup": "Showers look likely with temperatures near 74° / 44° and about 55% average precipitation signal plus wind around 21 mph. A sharp cooler turn follows the next day."
    },
    {
      "date": "2026-03-28",
      "sources": {
        "nws": {
          "date": "2026-03-28",
          "summary": "Slight Chance Rain And Snow Showers then Sunny",
          "precipProbability": 19,
          "windMph": 9,
          "rain": true,
          "snow": true,
          "thunder": false
        },
        "openMeteo": {
          "date": "2026-03-28",
          "summary": "Overcast",
          "precipProbability": 54,
          "windMph": 25.7,
          "rain": false,
          "snow": false,
          "thunder": false
        },
        "metNo": {
          "date": "2026-03-28",
          "summary": "Fair Night",
          "precipProbability": null,
          "windMph": 9.8,
          "rain": false,
          "snow": false,
          "thunder": false
        }
      },
      "consensus": {
        "rainSignal": "weak",
        "snowSignal": "weak",
        "thunderSignal": "off",
        "avgPrecipProbability": 36.5,
        "avgWindMph": 14.8,
        "windSignal": "medium",
        "summary": "Mostly quiet signal"
      },
      "writeup": "It looks breezy to windy with temperatures near 53° / 36° and about 37% average precipitation signal."
    },
    {
      "date": "2026-03-29",
      "sources": {
        "nws": {
          "date": "2026-03-29",
          "summary": "Sunny",
          "precipProbability": 7,
          "windMph": 7,
          "rain": false,
          "snow": false,
          "thunder": false
        },
        "openMeteo": {
          "date": "2026-03-29",
          "summary": "Mainly clear",
          "precipProbability": 4,
          "windMph": 23.3,
          "rain": false,
          "snow": false,
          "thunder": false
        },
        "metNo": {
          "date": "2026-03-29",
          "summary": "Clearsky Night",
          "precipProbability": null,
          "windMph": 6.9,
          "rain": false,
          "snow": false,
          "thunder": false
        }
      },
      "consensus": {
        "rainSignal": "off",
        "snowSignal": "off",
        "thunderSignal": "off",
        "avgPrecipProbability": 5.5,
        "avgWindMph": 12.4,
        "windSignal": "medium",
        "summary": "Mostly quiet signal"
      },
      "writeup": "It looks breezy to windy with temperatures near 60° / 41°."
    },
    {
      "date": "2026-03-30",
      "sources": {
        "nws": {
          "date": "2026-03-30",
          "summary": "Mostly Sunny",
          "precipProbability": 9,
          "windMph": 9,
          "rain": false,
          "snow": false,
          "thunder": false
        },
        "openMeteo": {
          "date": "2026-03-30",
          "summary": "Overcast",
          "precipProbability": 7,
          "windMph": 31.3,
          "rain": false,
          "snow": false,
          "thunder": false
        },
        "metNo": {
          "date": "2026-03-30",
          "summary": "Partlycloudy Night",
          "precipProbability": null,
          "windMph": 15.4,
          "rain": false,
          "snow": false,
          "thunder": false
        }
      },
      "consensus": {
        "rainSignal": "off",
        "snowSignal": "off",
        "thunderSignal": "off",
        "avgPrecipProbability": 8,
        "avgWindMph": 18.6,
        "windSignal": "strong",
        "summary": "Mostly quiet signal"
      },
      "writeup": "It looks breezy to windy with temperatures near 67° / 47° plus wind around 19 mph."
    }
  ]
}
